<?xml version="1.0" encoding="UTF-8"?>
<!DOCTYPE MODULE SYSTEM "VEES_V6.3.dtd">
<MODULE>
<!-- RECORD_LAYOUT BLOCKS -->
<RECORD_LAYOUT>
	<RECORD_ELT>
		<Name>ThrSpT_RL_Lookup1D_BYTE</Name>
		<RecordType>
			<FNC_VALUES/>
		</RecordType>
		<DataType>
			<SBYTE/>
		</DataType>
		<ReadOrder>
			<COLUMN_DIR/>
		</ReadOrder>
	</RECORD_ELT>
	<RECORD_ELT>
		<Name>ThrSpT_RL_Lookup1D_FLOAT32_IEEE</Name>
		<RecordType>
			<FNC_VALUES/>
		</RecordType>
		<DataType>
			<FLOAT32_IEEE/>
		</DataType>
		<ReadOrder>
			<COLUMN_DIR/>
		</ReadOrder>
	</RECORD_ELT>
	<RECORD_ELT>
		<Name>ThrSpT_RL_Lookup1D_FLOAT64_IEEE</Name>
		<RecordType>
			<FNC_VALUES/>
		</RecordType>
		<DataType>
			<FLOAT64_IEEE/>
		</DataType>
		<ReadOrder>
			<COLUMN_DIR/>
		</ReadOrder>
	</RECORD_ELT>
	<RECORD_ELT>
		<Name>ThrSpT_RL_Lookup1D_SLONG</Name>
		<RecordType>
			<FNC_VALUES/>
		</RecordType>
		<DataType>
			<SLONG/>
		</DataType>
		<ReadOrder>
			<COLUMN_DIR/>
		</ReadOrder>
	</RECORD_ELT>
	<RECORD_ELT>
		<Name>ThrSpT_RL_Lookup1D_UBYTE</Name>
		<RecordType>
			<FNC_VALUES/>
		</RecordType>
		<DataType>
			<UBYTE/>
		</DataType>
		<ReadOrder>
			<COLUMN_DIR/>
		</ReadOrder>
	</RECORD_ELT>
	<RECORD_ELT>
		<Name>ThrSpT_RL_Lookup1D_ULONG</Name>
		<RecordType>
			<FNC_VALUES/>
		</RecordType>
		<DataType>
			<ULONG/>
		</DataType>
		<ReadOrder>
			<COLUMN_DIR/>
		</ReadOrder>
	</RECORD_ELT>
	<RECORD_ELT>
		<Name>ThrSpT_RL_Lookup1D_UWORD</Name>
		<RecordType>
			<FNC_VALUES/>
		</RecordType>
		<DataType>
			<UWORD/>
		</DataType>
		<ReadOrder>
			<COLUMN_DIR/>
		</ReadOrder>
	</RECORD_ELT>
	<RECORD_ELT>
		<Name>ThrSpT_RL_Lookup1D_WORD</Name>
		<RecordType>
			<FNC_VALUES/>
		</RecordType>
		<DataType>
			<SWORD/>
		</DataType>
		<ReadOrder>
			<COLUMN_DIR/>
		</ReadOrder>
	</RECORD_ELT>
	<RECORD_ELT>
		<Name>ThrSpT_RL_Lookup1D_X_BYTE</Name>
		<RecordType>
			<BKPT/>
		</RecordType>
		<DataType>
			<SBYTE/>
		</DataType>
	</RECORD_ELT>
	<RECORD_ELT>
		<Name>ThrSpT_RL_Lookup1D_X_FLOAT32_IEEE</Name>
		<RecordType>
			<BKPT/>
		</RecordType>
		<DataType>
			<FLOAT32_IEEE/>
		</DataType>
	</RECORD_ELT>
	<RECORD_ELT>
		<Name>ThrSpT_RL_Lookup1D_X_FLOAT64_IEEE</Name>
		<RecordType>
			<BKPT/>
		</RecordType>
		<DataType>
			<FLOAT64_IEEE/>
		</DataType>
	</RECORD_ELT>
	<RECORD_ELT>
		<Name>ThrSpT_RL_Lookup1D_X_LONG</Name>
		<RecordType>
			<BKPT/>
		</RecordType>
		<DataType>
			<SLONG/>
		</DataType>
	</RECORD_ELT>
	<RECORD_ELT>
		<Name>ThrSpT_RL_Lookup1D_X_UBYTE</Name>
		<RecordType>
			<BKPT/>
		</RecordType>
		<DataType>
			<UBYTE/>
		</DataType>
	</RECORD_ELT>
	<RECORD_ELT>
		<Name>ThrSpT_RL_Lookup1D_X_ULONG</Name>
		<RecordType>
			<BKPT/>
		</RecordType>
		<DataType>
			<ULONG/>
		</DataType>
	</RECORD_ELT>
	<RECORD_ELT>
		<Name>ThrSpT_RL_Lookup1D_X_UWORD</Name>
		<RecordType>
			<BKPT/>
		</RecordType>
		<DataType>
			<UWORD/>
		</DataType>
	</RECORD_ELT>
	<RECORD_ELT>
		<Name>ThrSpT_RL_Lookup1D_X_WORD</Name>
		<RecordType>
			<BKPT/>
		</RecordType>
		<DataType>
			<SWORD/>
		</DataType>
	</RECORD_ELT>
	<RECORD_ELT>
		<Name>ThrSpT_RL_Lookup2D_BYTE</Name>
		<RecordType>
			<FNC_VALUES/>
		</RecordType>
		<DataType>
			<SBYTE/>
		</DataType>
		<ReadOrder>
			<COLUMN_DIR/>
		</ReadOrder>
	</RECORD_ELT>
	<RECORD_ELT>
		<Name>ThrSpT_RL_Lookup2D_FLOAT32_IEEE</Name>
		<RecordType>
			<FNC_VALUES/>
		</RecordType>
		<DataType>
			<FLOAT32_IEEE/>
		</DataType>
		<ReadOrder>
			<COLUMN_DIR/>
		</ReadOrder>
	</RECORD_ELT>
	<RECORD_ELT>
		<Name>ThrSpT_RL_Lookup2D_FLOAT64_IEEE</Name>
		<RecordType>
			<FNC_VALUES/>
		</RecordType>
		<DataType>
			<FLOAT64_IEEE/>
		</DataType>
		<ReadOrder>
			<COLUMN_DIR/>
		</ReadOrder>
	</RECORD_ELT>
	<RECORD_ELT>
		<Name>ThrSpT_RL_Lookup2D_LONG</Name>
		<RecordType>
			<FNC_VALUES/>
		</RecordType>
		<DataType>
			<SLONG/>
		</DataType>
		<ReadOrder>
			<COLUMN_DIR/>
		</ReadOrder>
	</RECORD_ELT>
	<RECORD_ELT>
		<Name>ThrSpT_RL_Lookup2D_UBYTE</Name>
		<RecordType>
			<FNC_VALUES/>
		</RecordType>
		<DataType>
			<UBYTE/>
		</DataType>
		<ReadOrder>
			<COLUMN_DIR/>
		</ReadOrder>
	</RECORD_ELT>
	<RECORD_ELT>
		<Name>ThrSpT_RL_Lookup2D_ULONG</Name>
		<RecordType>
			<FNC_VALUES/>
		</RecordType>
		<DataType>
			<ULONG/>
		</DataType>
		<ReadOrder>
			<COLUMN_DIR/>
		</ReadOrder>
	</RECORD_ELT>
	<RECORD_ELT>
		<Name>ThrSpT_RL_Lookup2D_UWORD</Name>
		<RecordType>
			<FNC_VALUES/>
		</RecordType>
		<DataType>
			<UWORD/>
		</DataType>
		<ReadOrder>
			<COLUMN_DIR/>
		</ReadOrder>
	</RECORD_ELT>
	<RECORD_ELT>
		<Name>ThrSpT_RL_Lookup2D_WORD</Name>
		<RecordType>
			<FNC_VALUES/>
		</RecordType>
		<DataType>
			<SWORD/>
		</DataType>
		<ReadOrder>
			<COLUMN_DIR/>
		</ReadOrder>
	</RECORD_ELT>
	<RECORD_ELT>
		<Name>ThrSpT_RL_Lookup2D_X_BYTE</Name>
		<RecordType>
			<BKPT/>
		</RecordType>
		<DataType>
			<SBYTE/>
		</DataType>
	</RECORD_ELT>
	<RECORD_ELT>
		<Name>ThrSpT_RL_Lookup2D_X_FLOAT32_IEEE</Name>
		<RecordType>
			<BKPT/>
		</RecordType>
		<DataType>
			<FLOAT32_IEEE/>
		</DataType>
	</RECORD_ELT>
	<RECORD_ELT>
		<Name>ThrSpT_RL_Lookup2D_X_FLOAT64_IEEE</Name>
		<RecordType>
			<BKPT/>
		</RecordType>
		<DataType>
			<FLOAT64_IEEE/>
		</DataType>
	</RECORD_ELT>
	<RECORD_ELT>
		<Name>ThrSpT_RL_Lookup2D_X_LONG</Name>
		<RecordType>
			<BKPT/>
		</RecordType>
		<DataType>
			<SLONG/>
		</DataType>
	</RECORD_ELT>
	<RECORD_ELT>
		<Name>ThrSpT_RL_Lookup2D_X_UBYTE</Name>
		<RecordType>
			<BKPT/>
		</RecordType>
		<DataType>
			<UBYTE/>
		</DataType>
	</RECORD_ELT>
	<RECORD_ELT>
		<Name>ThrSpT_RL_Lookup2D_X_ULONG</Name>
		<RecordType>
			<BKPT/>
		</RecordType>
		<DataType>
			<ULONG/>
		</DataType>
	</RECORD_ELT>
	<RECORD_ELT>
		<Name>ThrSpT_RL_Lookup2D_X_UWORD</Name>
		<RecordType>
			<BKPT/>
		</RecordType>
		<DataType>
			<UWORD/>
		</DataType>
	</RECORD_ELT>
	<RECORD_ELT>
		<Name>ThrSpT_RL_Lookup2D_X_WORD</Name>
		<RecordType>
			<BKPT/>
		</RecordType>
		<DataType>
			<SWORD/>
		</DataType>
	</RECORD_ELT>
	<RECORD_ELT>
		<Name>ThrSpT_RL_Scalar_BOOLEAN</Name>
		<RecordType>
			<FNC_VALUES/>
		</RecordType>
		<DataType>
			<UBYTE/>
		</DataType>
		<ReadOrder>
			<COLUMN_DIR/>
		</ReadOrder>
	</RECORD_ELT>
	<RECORD_ELT>
		<Name>ThrSpT_RL_Scalar_BYTE</Name>
		<RecordType>
			<FNC_VALUES/>
		</RecordType>
		<DataType>
			<SBYTE/>
		</DataType>
		<ReadOrder>
			<COLUMN_DIR/>
		</ReadOrder>
	</RECORD_ELT>
	<RECORD_ELT>
		<Name>ThrSpT_RL_Scalar_FLOAT32_IEEE</Name>
		<RecordType>
			<FNC_VALUES/>
		</RecordType>
		<DataType>
			<FLOAT32_IEEE/>
		</DataType>
		<ReadOrder>
			<COLUMN_DIR/>
		</ReadOrder>
	</RECORD_ELT>
	<RECORD_ELT>
		<Name>ThrSpT_RL_Scalar_FLOAT64_IEEE</Name>
		<RecordType>
			<FNC_VALUES/>
		</RecordType>
		<DataType>
			<FLOAT64_IEEE/>
		</DataType>
		<ReadOrder>
			<COLUMN_DIR/>
		</ReadOrder>
	</RECORD_ELT>
	<RECORD_ELT>
		<Name>ThrSpT_RL_Scalar_LONG</Name>
		<RecordType>
			<FNC_VALUES/>
		</RecordType>
		<DataType>
			<SLONG/>
		</DataType>
		<ReadOrder>
			<COLUMN_DIR/>
		</ReadOrder>
	</RECORD_ELT>
	<RECORD_ELT>
		<Name>ThrSpT_RL_Scalar_SWORD</Name>
		<RecordType>
			<FNC_VALUES/>
		</RecordType>
		<DataType>
			<SWORD/>
		</DataType>
		<ReadOrder>
			<COLUMN_DIR/>
		</ReadOrder>
	</RECORD_ELT>
	<RECORD_ELT>
		<Name>ThrSpT_RL_Scalar_UBYTE</Name>
		<RecordType>
			<FNC_VALUES/>
		</RecordType>
		<DataType>
			<UBYTE/>
		</DataType>
		<ReadOrder>
			<COLUMN_DIR/>
		</ReadOrder>
	</RECORD_ELT>
	<RECORD_ELT>
		<Name>ThrSpT_RL_Scalar_ULONG</Name>
		<RecordType>
			<FNC_VALUES/>
		</RecordType>
		<DataType>
			<ULONG/>
		</DataType>
		<ReadOrder>
			<COLUMN_DIR/>
		</ReadOrder>
	</RECORD_ELT>
	<RECORD_ELT>
		<Name>ThrSpT_RL_Scalar_UWORD</Name>
		<RecordType>
			<FNC_VALUES/>
		</RecordType>
		<DataType>
			<UWORD/>
		</DataType>
		<ReadOrder>
			<COLUMN_DIR/>
		</ReadOrder>
	</RECORD_ELT>
</RECORD_LAYOUT>
<!-- AXIS BLOCKS -->
<AXIS>
</AXIS>
<!-- CHARACTERISTIC BLOCKS -->
<CHARACTERISTICS>
	<CHARACTERISTIC>
		<Name>THRSPT_ACTIVE_BYP_C</Name>
		<LongIdentifier>calibration de bypass</LongIdentifier>
		<Deposit>ThrSpT_RL_Scalar_BOOLEAN</Deposit>
		<DataType>
			<UBYTE/>
		</DataType>
		<RefConversion>ThrSpT_CM_Boolean</RefConversion>
		<PhysicalLowerLimit>0</PhysicalLowerLimit>
		<PhysicalUpperLimit>1.0</PhysicalUpperLimit>
		<DecLowerLimit/>
		<DecUpperLimit/>
		<CHARACTERISTIC_TYPE>
			<VALUE/>
		</CHARACTERISTIC_TYPE>
		<ECU_ADDRESS>0x0</ECU_ADDRESS>
	</CHARACTERISTIC>
	<CHARACTERISTIC>
		<Name>ThrSys_arMaxSpdAdpThr_C</Name>
		<LongIdentifier>Adaptatif papillon maximum</LongIdentifier>
		<Deposit>ThrSpT_RL_Scalar_SWORD</Deposit>
		<DataType>
			<SWORD/>
		</DataType>
		<RefConversion>ThrSpT_CM_5</RefConversion>
		<PhysicalLowerLimit>-0.000128</PhysicalLowerLimit>
		<PhysicalUpperLimit>1.2799609374999999E-004</PhysicalUpperLimit>
		<DecLowerLimit>-32768</DecLowerLimit>
		<DecUpperLimit>32767</DecUpperLimit>
		<CHARACTERISTIC_TYPE>
			<VALUE/>
		</CHARACTERISTIC_TYPE>
		<ECU_ADDRESS>0x0</ECU_ADDRESS>
	</CHARACTERISTIC>
	<CHARACTERISTIC>
		<Name>ThrSys_arMinSpdAdpThr_C</Name>
		<LongIdentifier>Adaptatif papillon minimum.</LongIdentifier>
		<Deposit>ThrSpT_RL_Scalar_SWORD</Deposit>
		<DataType>
			<SWORD/>
		</DataType>
		<RefConversion>ThrSpT_CM_5</RefConversion>
		<PhysicalLowerLimit>-0.000128</PhysicalLowerLimit>
		<PhysicalUpperLimit>1.2799609374999999E-004</PhysicalUpperLimit>
		<DecLowerLimit>-32768</DecLowerLimit>
		<DecUpperLimit>32767</DecUpperLimit>
		<CHARACTERISTIC_TYPE>
			<VALUE/>
		</CHARACTERISTIC_TYPE>
		<ECU_ADDRESS>0x0</ECU_ADDRESS>
	</CHARACTERISTIC>
	<CHARACTERISTIC>
		<Name>ThrSys_arStepSpdAdpThr_C</Name>
		<LongIdentifier>Incrément de section pour ladaptation de la section efficace papillon</LongIdentifier>
		<Deposit>ThrSpT_RL_Scalar_UWORD</Deposit>
		<DataType>
			<UWORD/>
		</DataType>
		<RefConversion>ThrSpT_CM_5</RefConversion>
		<PhysicalLowerLimit>0</PhysicalLowerLimit>
		<PhysicalUpperLimit>2.5599609374999998E-004</PhysicalUpperLimit>
		<DecLowerLimit>0</DecLowerLimit>
		<DecUpperLimit>65535</DecUpperLimit>
		<CHARACTERISTIC_TYPE>
			<VALUE/>
		</CHARACTERISTIC_TYPE>
		<ECU_ADDRESS>0x0</ECU_ADDRESS>
	</CHARACTERISTIC>
	<CHARACTERISTIC>
		<Name>ThrSys_rOpThrReq_B</Name>
		<LongIdentifier>Consigne de position corrigée boîtier papillon motorisé Dim = 1x1 (Bypass)</LongIdentifier>
		<Deposit>ThrSpT_RL_Scalar_UWORD</Deposit>
		<DataType>
			<UWORD/>
		</DataType>
		<RefConversion>ThrSpT_CM_1</RefConversion>
		<PhysicalLowerLimit>0</PhysicalLowerLimit>
		<PhysicalUpperLimit>1.0</PhysicalUpperLimit>
		<DecLowerLimit>0</DecLowerLimit>
		<DecUpperLimit>1024</DecUpperLimit>
		<CHARACTERISTIC_TYPE>
			<VALUE/>
		</CHARACTERISTIC_TYPE>
		<ECU_ADDRESS>0x0</ECU_ADDRESS>
	</CHARACTERISTIC>
	<CHARACTERISTIC>
		<Name>ThrSys_tiDlyStabSign_mAirInt_C</Name>
		<LongIdentifier>Durée de stabilité avant adaptation.</LongIdentifier>
		<Deposit>ThrSpT_RL_Scalar_UWORD</Deposit>
		<DataType>
			<UWORD/>
		</DataType>
		<RefConversion>ThrSpT_CM_4</RefConversion>
		<PhysicalLowerLimit>0</PhysicalLowerLimit>
		<PhysicalUpperLimit>65.535</PhysicalUpperLimit>
		<DecLowerLimit>0</DecLowerLimit>
		<DecUpperLimit>65535</DecUpperLimit>
		<CHARACTERISTIC_TYPE>
			<VALUE/>
		</CHARACTERISTIC_TYPE>
		<ECU_ADDRESS>0x0</ECU_ADDRESS>
	</CHARACTERISTIC>
</CHARACTERISTICS>
<!-- MEASUREMENT BLOCKS -->
<MEASUREMENTS>
	<MEASUREMENT>
		<Name>ThrSpT_ModuleVersion_Major_MP</Name>
		<LongIdentifier>Major version number</LongIdentifier>
		<DataType>
			<UBYTE/>
		</DataType>
		<RefConversion>ThrSpT_CM_Version</RefConversion>
		<PhysicalLowerLimit>0</PhysicalLowerLimit>
		<PhysicalUpperLimit>255</PhysicalUpperLimit>
		<DecLowerLimit>0</DecLowerLimit>
		<DecUpperLimit>255</DecUpperLimit>
		<ResolutionIfDefined>0</ResolutionIfDefined>
		<READ_ONLY/>
		<ECU_ADDRESS>0x0</ECU_ADDRESS>
	</MEASUREMENT>
	<MEASUREMENT>
		<Name>ThrSpT_ModuleVersion_Minor_MP</Name>
		<LongIdentifier>Minor version number</LongIdentifier>
		<DataType>
			<UBYTE/>
		</DataType>
		<RefConversion>ThrSpT_CM_Version</RefConversion>
		<PhysicalLowerLimit>0</PhysicalLowerLimit>
		<PhysicalUpperLimit>255</PhysicalUpperLimit>
		<DecLowerLimit>0</DecLowerLimit>
		<DecUpperLimit>255</DecUpperLimit>
		<ResolutionIfDefined>0</ResolutionIfDefined>
		<READ_ONLY/>
		<ECU_ADDRESS>0x0</ECU_ADDRESS>
	</MEASUREMENT>
	<MEASUREMENT>
		<Name>ThrSpT_ModuleVersion_Patch_MP</Name>
		<LongIdentifier>Patch version number</LongIdentifier>
		<DataType>
			<UBYTE/>
		</DataType>
		<RefConversion>ThrSpT_CM_Version</RefConversion>
		<PhysicalLowerLimit>0</PhysicalLowerLimit>
		<PhysicalUpperLimit>255</PhysicalUpperLimit>
		<DecLowerLimit>0</DecLowerLimit>
		<DecUpperLimit>255</DecUpperLimit>
		<ResolutionIfDefined>0</ResolutionIfDefined>
		<READ_ONLY/>
		<ECU_ADDRESS>0x0</ECU_ADDRESS>
	</MEASUREMENT>
	<MEASUREMENT>
		<Name>ThrSys_arOpEffThrOfs</Name>
		<LongIdentifier>Offset de section issu de ladaptatif lent</LongIdentifier>
		<DataType>
			<FLOAT32_IEEE/>
		</DataType>
		<RefConversion>ThrSpT_CM_7</RefConversion>
		<PhysicalLowerLimit>-0.001953125</PhysicalLowerLimit>
		<PhysicalUpperLimit>1.9530653953552240E-003</PhysicalUpperLimit>
		<DecLowerLimit>-0.001953125</DecLowerLimit>
		<DecUpperLimit>0.0019530653953552</DecUpperLimit>
		<ResolutionIfDefined>0</ResolutionIfDefined>
		<READ_ONLY/>
		<ECU_ADDRESS>0x0</ECU_ADDRESS>
	</MEASUREMENT>
	<MEASUREMENT>
		<Name>ThrSys_arSpdAdpThr_IRV_MP</Name>
		<LongIdentifier>-</LongIdentifier>
		<DataType>
			<SLONG/>
		</DataType>
		<RefConversion>ThrSpT_CM_8</RefConversion>
		<PhysicalLowerLimit>-0.000128</PhysicalLowerLimit>
		<PhysicalUpperLimit>1.2799609374999999E-004</PhysicalUpperLimit>
		<DecLowerLimit>-34359.738368</DecLowerLimit>
		<DecUpperLimit>34358.689792</DecUpperLimit>
		<ResolutionIfDefined>0</ResolutionIfDefined>
		<READ_ONLY/>
		<ECU_ADDRESS>0x0</ECU_ADDRESS>
	</MEASUREMENT>
	<MEASUREMENT>
		<Name>ThrSys_arThrCor_MP</Name>
		<LongIdentifier>Aire efficace moins les offset rapide, offset lent et le biais</LongIdentifier>
		<DataType>
			<UWORD/>
		</DataType>
		<RefConversion>ThrSpT_CM_9</RefConversion>
		<PhysicalLowerLimit>0</PhysicalLowerLimit>
		<PhysicalUpperLimit>3.9061903953552242E-003</PhysicalUpperLimit>
		<DecLowerLimit>0</DecLowerLimit>
		<DecUpperLimit>65535</DecUpperLimit>
		<ResolutionIfDefined>0</ResolutionIfDefined>
		<READ_ONLY/>
		<ECU_ADDRESS>0x0</ECU_ADDRESS>
	</MEASUREMENT>
	<MEASUREMENT>
		<Name>ThrSys_bAcvSpdAdpThr</Name>
		<LongIdentifier>Booléen dactivation de ladaptation rapide de la section papillon</LongIdentifier>
		<DataType>
			<UBYTE/>
		</DataType>
		<RefConversion>ThrSpT_CM_Boolean</RefConversion>
		<PhysicalLowerLimit>0</PhysicalLowerLimit>
		<PhysicalUpperLimit>1.0</PhysicalUpperLimit>
		<DecLowerLimit/>
		<DecUpperLimit/>
		<ResolutionIfDefined>0</ResolutionIfDefined>
		<BIT_MASK>0x01</BIT_MASK>
		<READ_ONLY/>
		<ECU_ADDRESS>0x0</ECU_ADDRESS>
	</MEASUREMENT>
	<MEASUREMENT>
		<Name>ThrSys_bAdpThrSign_mAirInt</Name>
		<LongIdentifier>Signe de lintégrateur pour ladaptation de la section efficace</LongIdentifier>
		<DataType>
			<UBYTE/>
		</DataType>
		<RefConversion>ThrSpT_CM_Boolean</RefConversion>
		<PhysicalLowerLimit>0</PhysicalLowerLimit>
		<PhysicalUpperLimit>1.0</PhysicalUpperLimit>
		<DecLowerLimit/>
		<DecUpperLimit/>
		<ResolutionIfDefined>0</ResolutionIfDefined>
		<BIT_MASK>0x01</BIT_MASK>
		<READ_ONLY/>
		<ECU_ADDRESS>0x0</ECU_ADDRESS>
	</MEASUREMENT>
	<MEASUREMENT>
		<Name>ThrSys_bAdpThrSign_mIntPrev</Name>
		<LongIdentifier>Signe de lintégrateur pour ladaptation de la section efficace au pas précédent</LongIdentifier>
		<DataType>
			<UBYTE/>
		</DataType>
		<RefConversion>ThrSpT_CM_Boolean</RefConversion>
		<PhysicalLowerLimit>0</PhysicalLowerLimit>
		<PhysicalUpperLimit>1.0</PhysicalUpperLimit>
		<DecLowerLimit/>
		<DecUpperLimit/>
		<ResolutionIfDefined>0</ResolutionIfDefined>
		<BIT_MASK>0x01</BIT_MASK>
		<READ_ONLY/>
		<ECU_ADDRESS>0x0</ECU_ADDRESS>
	</MEASUREMENT>
	<MEASUREMENT>
		<Name>ThrSys_rOpThrNom</Name>
		<LongIdentifier>Position papillon calculée à partir de la cartographie nominale et de laire efficace</LongIdentifier>
		<DataType>
			<UWORD/>
		</DataType>
		<RefConversion>ThrSpT_CM_1</RefConversion>
		<PhysicalLowerLimit>0</PhysicalLowerLimit>
		<PhysicalUpperLimit>1.0</PhysicalUpperLimit>
		<DecLowerLimit>0</DecLowerLimit>
		<DecUpperLimit>1024</DecUpperLimit>
		<ResolutionIfDefined>0</ResolutionIfDefined>
		<READ_ONLY/>
		<ECU_ADDRESS>0x0</ECU_ADDRESS>
	</MEASUREMENT>
	<MEASUREMENT>
		<Name>ThrSys_rOpThrNomRef2_MP</Name>
		<LongIdentifier>Point de mesure de la position papillon calculée à partir de la cartographie nominale et de laire efficace Ref2</LongIdentifier>
		<DataType>
			<UWORD/>
		</DataType>
		<RefConversion>ThrSpT_CM_1</RefConversion>
		<PhysicalLowerLimit>0</PhysicalLowerLimit>
		<PhysicalUpperLimit>1.0</PhysicalUpperLimit>
		<DecLowerLimit>0</DecLowerLimit>
		<DecUpperLimit>1024</DecUpperLimit>
		<ResolutionIfDefined>0</ResolutionIfDefined>
		<READ_ONLY/>
		<ECU_ADDRESS>0x0</ECU_ADDRESS>
	</MEASUREMENT>
	<MEASUREMENT>
		<Name>ThrSys_rOpThrNomRef3_MP</Name>
		<LongIdentifier>Point de mesure de la position papillon calculée à partir de la cartographie nominale et de laire efficace Ref3</LongIdentifier>
		<DataType>
			<UWORD/>
		</DataType>
		<RefConversion>ThrSpT_CM_1</RefConversion>
		<PhysicalLowerLimit>0</PhysicalLowerLimit>
		<PhysicalUpperLimit>1.0</PhysicalUpperLimit>
		<DecLowerLimit>0</DecLowerLimit>
		<DecUpperLimit>1024</DecUpperLimit>
		<ResolutionIfDefined>0</ResolutionIfDefined>
		<READ_ONLY/>
		<ECU_ADDRESS>0x0</ECU_ADDRESS>
	</MEASUREMENT>
	<MEASUREMENT>
		<Name>ThrSys_rOpThrNomSat_MP</Name>
		<LongIdentifier>Point de mesure de la position papillon calculée à partir de la cartographie nominale et de laire efficace saturée</LongIdentifier>
		<DataType>
			<UWORD/>
		</DataType>
		<RefConversion>ThrSpT_CM_1</RefConversion>
		<PhysicalLowerLimit>0</PhysicalLowerLimit>
		<PhysicalUpperLimit>1.0</PhysicalUpperLimit>
		<DecLowerLimit>0</DecLowerLimit>
		<DecUpperLimit>1024</DecUpperLimit>
		<ResolutionIfDefined>0</ResolutionIfDefined>
		<READ_ONLY/>
		<ECU_ADDRESS>0x0</ECU_ADDRESS>
	</MEASUREMENT>
	<MEASUREMENT>
		<Name>ThrSys_tiStabSign_mAirInt</Name>
		<LongIdentifier>Compteur du délai de stabilité avant adaptation</LongIdentifier>
		<DataType>
			<UWORD/>
		</DataType>
		<RefConversion>ThrSpT_CM_4</RefConversion>
		<PhysicalLowerLimit>0</PhysicalLowerLimit>
		<PhysicalUpperLimit>65.535</PhysicalUpperLimit>
		<DecLowerLimit>0</DecLowerLimit>
		<DecUpperLimit>65535</DecUpperLimit>
		<ResolutionIfDefined>0</ResolutionIfDefined>
		<READ_ONLY/>
		<ECU_ADDRESS>0x0</ECU_ADDRESS>
	</MEASUREMENT>
	<MEASUREMENT>
		<Name>ThrSys_tiStabSign_mIntPrev</Name>
		<LongIdentifier>Compteur du délai de stabilité  avant adaptation au pas précédent</LongIdentifier>
		<DataType>
			<UWORD/>
		</DataType>
		<RefConversion>ThrSpT_CM_4</RefConversion>
		<PhysicalLowerLimit>0</PhysicalLowerLimit>
		<PhysicalUpperLimit>65.535</PhysicalUpperLimit>
		<DecLowerLimit>0</DecLowerLimit>
		<DecUpperLimit>65535</DecUpperLimit>
		<ResolutionIfDefined>0</ResolutionIfDefined>
		<READ_ONLY/>
		<ECU_ADDRESS>0x0</ECU_ADDRESS>
	</MEASUREMENT>
</MEASUREMENTS>
<!-- COMPU_METHOD BLOCKS -->
<COMPU_METHODS>
	<COMPU_METHOD>
		<Name>ThrSpT_CM_1</Name>
		<LongIdentifier>Q = V*1024</LongIdentifier>
		<Format>%0.6</Format>
		<Unit>-</Unit>
		<COMPU_TYPE>
			<RAT_FUNC>
				<Num2>0</Num2>
				<Num1>1024</Num1>
				<Num0>0</Num0>
				<Den2>0</Den2>
				<Den1>0</Den1>
				<Den0>1</Den0>
			</RAT_FUNC>
		</COMPU_TYPE>
	</COMPU_METHOD>
	<COMPU_METHOD>
		<Name>ThrSpT_CM_2</Name>
		<LongIdentifier>Q = V*16777216</LongIdentifier>
		<Format>%0.6</Format>
		<Unit>m2</Unit>
		<COMPU_TYPE>
			<RAT_FUNC>
				<Num2>0</Num2>
				<Num1>16777216</Num1>
				<Num0>0</Num0>
				<Den2>0</Den2>
				<Den1>0</Den1>
				<Den0>1</Den0>
			</RAT_FUNC>
		</COMPU_TYPE>
	</COMPU_METHOD>
	<COMPU_METHOD>
		<Name>ThrSpT_CM_3</Name>
		<LongIdentifier>Q = V*1024</LongIdentifier>
		<Format>%0.6</Format>
		<Unit>%</Unit>
		<COMPU_TYPE>
			<RAT_FUNC>
				<Num2>0</Num2>
				<Num1>1024</Num1>
				<Num0>0</Num0>
				<Den2>0</Den2>
				<Den1>0</Den1>
				<Den0>1</Den0>
			</RAT_FUNC>
		</COMPU_TYPE>
	</COMPU_METHOD>
	<COMPU_METHOD>
		<Name>ThrSpT_CM_4</Name>
		<LongIdentifier>Q = V*1000</LongIdentifier>
		<Format>%0.6</Format>
		<Unit>s</Unit>
		<COMPU_TYPE>
			<RAT_FUNC>
				<Num2>0</Num2>
				<Num1>1000</Num1>
				<Num0>0</Num0>
				<Den2>0</Den2>
				<Den1>0</Den1>
				<Den0>1</Den0>
			</RAT_FUNC>
		</COMPU_TYPE>
	</COMPU_METHOD>
	<COMPU_METHOD>
		<Name>ThrSpT_CM_5</Name>
		<LongIdentifier>Q = V*256000000</LongIdentifier>
		<Format>%0.6</Format>
		<Unit>m²</Unit>
		<COMPU_TYPE>
			<RAT_FUNC>
				<Num2>0</Num2>
				<Num1>256000000</Num1>
				<Num0>0</Num0>
				<Den2>0</Den2>
				<Den1>0</Den1>
				<Den0>1</Den0>
			</RAT_FUNC>
		</COMPU_TYPE>
	</COMPU_METHOD>
	<COMPU_METHOD>
		<Name>ThrSpT_CM_7</Name>
		<LongIdentifier>Q = V</LongIdentifier>
		<Format>%0.6</Format>
		<Unit>m²</Unit>
		<COMPU_TYPE>
			<RAT_FUNC>
				<Num2>0</Num2>
				<Num1>1</Num1>
				<Num0>0</Num0>
				<Den2>0</Den2>
				<Den1>0</Den1>
				<Den0>1</Den0>
			</RAT_FUNC>
		</COMPU_TYPE>
	</COMPU_METHOD>
	<COMPU_METHOD>
		<Name>ThrSpT_CM_8</Name>
		<LongIdentifier>Q = V*268435456</LongIdentifier>
		<Format>%0.6</Format>
		<Unit>m²</Unit>
		<COMPU_TYPE>
			<RAT_FUNC>
				<Num2>0</Num2>
				<Num1>268435456</Num1>
				<Num0>0</Num0>
				<Den2>0</Den2>
				<Den1>0</Den1>
				<Den0>1</Den0>
			</RAT_FUNC>
		</COMPU_TYPE>
	</COMPU_METHOD>
	<COMPU_METHOD>
		<Name>ThrSpT_CM_9</Name>
		<LongIdentifier>Q = V*16777216</LongIdentifier>
		<Format>%0.6</Format>
		<Unit>m²</Unit>
		<COMPU_TYPE>
			<RAT_FUNC>
				<Num2>0</Num2>
				<Num1>16777216</Num1>
				<Num0>0</Num0>
				<Den2>0</Den2>
				<Den1>0</Den1>
				<Den0>1</Den0>
			</RAT_FUNC>
		</COMPU_TYPE>
	</COMPU_METHOD>
	<COMPU_METHOD>
		<Name>ThrSpT_CM_Boolean</Name>
		<LongIdentifier>Boolean</LongIdentifier>
		<Format>%0.0</Format>
		<Unit>-</Unit>
		<COMPU_TYPE>
			<COMPU_VTAB>
				<VALUE_PAIR>
					<InVal>0</InVal>
					<OutVal>FALSE</OutVal>
				</VALUE_PAIR>
				<VALUE_PAIR>
					<InVal>1</InVal>
					<OutVal>TRUE</OutVal>
				</VALUE_PAIR>
			</COMPU_VTAB>
		</COMPU_TYPE>
	</COMPU_METHOD>
	<COMPU_METHOD>
		<Name>ThrSpT_CM_Version</Name>
		<LongIdentifier>Q = V</LongIdentifier>
		<Format>%0.6</Format>
		<Unit>-</Unit>
		<COMPU_TYPE>
			<RAT_FUNC>
				<Num2>0</Num2>
				<Num1>1.000000000</Num1>
				<Num0>0.000000000</Num0>
				<Den2>0</Den2>
				<Den1>0</Den1>
				<Den0>1.000000000</Den0>
			</RAT_FUNC>
		</COMPU_TYPE>
	</COMPU_METHOD>
</COMPU_METHODS>
<!-- FUNCTION BLOCKS -->
<FUNCTIONS>
	<FUNCTION>
		<Name>ThrSpT_FCT_ThrSpT</Name>
		<LongIdentifier>CHARACTERISTIC and MEASUREMENT of ThrSpT Software Component</LongIdentifier>
		<DEF_CHARACTERISTICS>
			<Name>THRSPT_ACTIVE_BYP_C</Name>
			<Name>ThrSys_arMaxSpdAdpThr_C</Name>
			<Name>ThrSys_arMinSpdAdpThr_C</Name>
			<Name>ThrSys_arStepSpdAdpThr_C</Name>
			<Name>ThrSys_rOpThrReq_B</Name>
			<Name>ThrSys_tiDlyStabSign_mAirInt_C</Name>
		</DEF_CHARACTERISTICS>
		<LOC_MEASUREMENTS>
			<Name>ThrSpT_ModuleVersion_Major_MP</Name>
			<Name>ThrSpT_ModuleVersion_Minor_MP</Name>
			<Name>ThrSpT_ModuleVersion_Patch_MP</Name>
			<Name>ThrSys_arOpEffThrOfs</Name>
			<Name>ThrSys_arSpdAdpThr_IRV_MP</Name>
			<Name>ThrSys_arThrCor_MP</Name>
			<Name>ThrSys_bAcvSpdAdpThr</Name>
			<Name>ThrSys_bAdpThrSign_mAirInt</Name>
			<Name>ThrSys_bAdpThrSign_mIntPrev</Name>
			<Name>ThrSys_rOpThrNom</Name>
			<Name>ThrSys_rOpThrNomRef2_MP</Name>
			<Name>ThrSys_rOpThrNomRef3_MP</Name>
			<Name>ThrSys_rOpThrNomSat_MP</Name>
			<Name>ThrSys_tiStabSign_mAirInt</Name>
			<Name>ThrSys_tiStabSign_mIntPrev</Name>
		</LOC_MEASUREMENTS>
	</FUNCTION>
</FUNCTIONS>
<!-- GROUP BLOCKS -->
<GROUPS>
</GROUPS>
<!-- STRUCTURE BLOCKS -->
<STRUCTURES>
</STRUCTURES>
<!-- STRUCTURE_INSTANCE BLOCKS -->
<STRUCTURE_INSTANCES>
</STRUCTURE_INSTANCES>
</MODULE>
